{
	"name": "A_CommandCenterPricingSkuPrioritizationDquScanCZCustomersProducts",
	"properties": {
		"annotations": [],
		"runtimeState": "Stopped",
		"pipelines": [
			{
				"pipelineReference": {
					"referenceName": "0_SkuPrioritization_DataQuality_Scan_CZ_Customers_Products_PPL",
					"type": "PipelineReference"
				}
			}
		],
		"type": "ScheduleTrigger",
		"typeProperties": {
			"recurrence": {
				"frequency": "Week",
				"interval": 1,
				"startTime": "2022-10-27T20:24:00",
				"timeZone": "E. South America Standard Time",
				"schedule": {
					"minutes": [
						0
					],
					"hours": [
						21
					],
					"weekDays": [
						"Sunday"
					]
				}
			}
		}
	}
}